uvartage/__init__.py
uvartage/__main__.py
uvartage/backends.py
uvartage/commons.py
uvartage/loop.py
uvartage/py.typed
uvartage-0.4.1.dist-info/WHEEL
uvartage-0.4.1.dist-info/entry_points.txt
uvartage-0.4.1.dist-info/METADATA
uvartage-0.4.1.dist-info/RECORD
