Metadata-Version: 2.3
Name: uvartage
Version: 0.4.1
Summary: Wrapper for uv with artifact storage in airgapped environments
Author: Rainer Schwarzbach
Author-email: Rainer Schwarzbach <rainer@blackstream.de>
Classifier: Development Status :: 4 - Beta
Classifier: License :: OSI Approved :: MIT License
Classifier: Operating System :: OS Independent
Classifier: Environment :: Console
Classifier: Programming Language :: Python :: 3
Classifier: Programming Language :: Python :: 3.11
Classifier: Programming Language :: Python :: 3.12
Classifier: Programming Language :: Python :: 3.13
Classifier: Programming Language :: Python :: 3.14
Classifier: Programming Language :: Python :: 3 :: Only
Classifier: Topic :: Utilities
Classifier: Typing :: Typed
Classifier: Intended Audience :: Developers
Requires-Dist: pyreadline3 ; sys_platform == 'win32'
Requires-Python: >=3.11
Project-URL: Bug Tracker, https://gitlab.com/blackstream-x/uvartage/-/issues
Project-URL: CI, https://gitlab.com/blackstream-x/uvartage/-/pipelines
Project-URL: Homepage, https://gitlab.com/blackstream-x/uvartage
Project-URL: Repository, https://gitlab.com/blackstream-x/uvartage.git
